Workbook

Sheet Harvest Records
A1: No | B1: Crop | C1: Variety | D1: Planting Date | E1: Est. Harvest Date | F1: Actual Harvest Date | G1: Quantity Harvested | H1: Unit | I1: Price per Unit (LKR) | J1: Total Revenue (LKR) | K1: Seed/Planting (LKR) | L1: Fertilizer (LKR) | M1: Pesticide/Herbicide (LKR) | N1: Machinery/Harvesting Charge (LKR) | O1: Total Expenses (LKR) | P1: Net Profit (LKR)
A2: 1 | B2: Paddy | C2: BG 250 | D2: 45570 | E2: 45690 | F2: 45691 | G2: 202 | H2: kg | I2: 127.91 | J2: =G2*I2 -> 25837.82 | K2: 3789.65 | L2: 8338 | M2: 3642.55 | N2: 9658.91 | O2: =SUM(K2:N2) -> 25429.11 | P2: =J2-O2 -> 408.71
A3: 2 | B3: Paddy | C3: BG 300 (Improved) | D3: 45785 | E3: 45905 | F3: 45906 | G3: 134 | H3: kg | I3: 126.39 | J3: =G3*I3 -> 16936.26 | K3: 3429.4 | L3: 8601.63 | M3: 2836.34 | N3: 10684.64 | O3: =SUM(K3:N3) -> 25552.01 | P3: =J3-O3 -> -8615.75
A4: 3 | B4: Paddy | C4: BG 250 | D4: 45942 | E4: 46062 | F4: 46063 | G4: 228 | H4: kg | I4: 92.36 | J4: =G4*I4 -> 21058.08 | K4: 4130.91 | L4: 14632.15 | M4: 3261.25 | N4: 13080.98 | O4: =SUM(K4:N4) -> 35105.29 | P4: =J4-O4 -> -14047.21
A5: 4 | B5: Paddy | C5: BW 372 | D5: 45426 | E5: 45546 | F5: 45549 | G5: 135 | H5: kg | I5: 113.08 | J5: =G5*I5 -> 15265.8 | K5: 3793.36 | L5: 14833.79 | M5: 2093.17 | N5: 15009.28 | O5: =SUM(K5:N5) -> 35729.6 | P5: =J5-O5 -> -20463.8
A6: 5 | B6: Paddy | C6: BG 250 | D6: 45573 | E6: 45693 | F6: 45688 | G6: 194 | H6: kg | I6: 106.77 | J6: =G6*I6 -> 20713.38 | K6: 4081.37 | L6: 11996.4 | M6: 3120.51 | N6: 13774.02 | O6: =SUM(K6:N6) -> 32972.3 | P6: =J6-O6 -> -12258.92
A7: 6 | B7: Paddy | C7: BW 372 | D7: 45789 | E7: 45909 | F7: 45914 | G7: 146 | H7: kg | I7: 113.26 | J7: =G7*I7 -> 16535.96 | K7: 4277.83 | L7: 10606.78 | M7: 3095.49 | N7: 9439.52 | O7: =SUM(K7:N7) -> 27419.62 | P7: =J7-O7 -> -10883.66
A8: 7 | B8: Paddy | C8: BG 250 | D8: 45945 | E8: 46065 | F8: 46065 | G8: 135 | H8: kg | I8: 114.76 | J8: =G8*I8 -> 15492.6 | K8: 3992.83 | L8: 11722.04 | M8: 3554.46 | N8: 12259.21 | O8: =SUM(K8:N8) -> 31528.54 | P8: =J8-O8 -> -16035.94
A9: 8 | B9: Tomato | C9: Thilina F1 | D9: 45306 | E9: 45396 | F9: 45399 | G9: 138 | H9: kg | I9: 96.16 | J9: =G9*I9 -> 13270.08 | K9: 2496.85 | L9: 5719.07 | M9: 5339.49 | N9: 2163.71 | O9: =SUM(K9:N9) -> 15719.12 | P9: =J9-O9 -> -2449.04
A10: 9 | B10: Brinjal | C10: Local Long Purple | D10: 45417 | E10: 45517 | F10: 45520 | G10: 98 | H10: kg | I10: 116.76 | J10: =G10*I10 -> 11442.48 | K10: 2812.71 | L10: 6917.78 | M10: 3219.84 | N10: 2970.26 | O10: =SUM(K10:N10) -> 15920.59 | P10: =J10-O10 -> -4478.11
A11: 10 | B11: Tomato | C11: Thilina F1 | D11: 45566 | E11: 45656 | F11: 45651 | G11: 95 | H11: kg | I11: 111.19 | J11: =G11*I11 -> 10563.05 | K11: 2329.92 | L11: 6368.22 | M11: 5799.81 | N11: 2843.4 | O11: =SUM(K11:N11) -> 17341.35 | P11: =J11-O11 -> -6778.3
A12: 11 | B12: Brinjal | C12: Local Long Purple | D12: 45698 | E12: 45798 | F12: 45794 | G12: 69 | H12: kg | I12: 133.52 | J12: =G12*I12 -> 9212.88 | K12: 2359.54 | L12: 7501.91 | M12: 3284.37 | N12: 2542.94 | O12: =SUM(K12:N12) -> 15688.76 | P12: =J12-O12 -> -6475.88
A13: 12 | B13: Tomato | C13: Thilina F1 | D13: 45843 | E13: 45933 | F13: 45927 | G13: 156 | H13: kg | I13: 109.67 | J13: =G13*I13 -> 17108.52 | K13: 3593.78 | L13: 5275.05 | M13: 3280.79 | N13: 2539.88 | O13: =SUM(K13:N13) -> 14689.5 | P13: =J13-O13 -> 2419.02
... A38: 37 | B38: Ladies Finger | C38: Haritha | D38: 45818 | E38: 45878 | F38: 45878 | G38: 93 | H38: kg | I38: 125.95 | J38: =G38*I38 -> 11713.35 | K38: 1889.01 | L38: 3584.81 | M38: 2453.76 | N38: 1086.75 | O38: =SUM(K38:N38) -> 9014.33 | P38: =J38-O38 -> 2699.02
F40: TOTAL | G40: =SUM(G2:G38) -> 4631 | J40: =SUM(J2:J38) -> 650637.91 | O40: =SUM(O2:O38) -> 601124.38 | P40: =SUM(P2:P38) -> 49513.53
B42: Note: Quantity, Price, and all expense figures (seed/planting material, fertilizer, pesticide/herbicide, machinery/harvesting charge - tractor, thresher, sprayer rental, transport etc.) are estimated, scaled to a small home/demo farm plot, using approximate 2024-2026 Sri Lankan farmgate prices and typical smallholder input costs (LKR). Coconut is priced per nut, not per kg. Net Profit = Total Revenue - Total Expenses. Replace any column with your own figures - all totals recalculate automatically.

Sheet Summary by Crop
A1: Crop | B1: No. of Batches | C1: Total Quantity | D1: Unit | E1: Avg. Price/Unit (LKR) | F1: Total Revenue (LKR) | G1: Total Expenses (LKR) | H1: Net Profit (LKR) | I1: Profit Margin (%)
A2: Paddy | B2: =COUNTIF('Harvest Records'!B:B,A2) -> 8 | C2: =SUMIF('Harvest Records'!B:B,A2,'Harvest Records'!G:G) -> 1418 | D2: kg | E2: =IFERROR(SUMIF('Harvest Records'!B:B,A2,'Harvest Records'!J:J)/C2,0) -> 114.18227 | F2: =SUMIF('Harvest Records'!B:B,A2,'Harvest Records'!J:J) -> 161910.46 | G2: =SUMIF('Harvest Records'!B:B,A2,'Harvest Records'!O:O) -> 242108.17 | H2: =F2-G2 -> -80197.71 | I2: =IFERROR(H2/F2*100,0) -> -49.532136
A3: Tomato | B3: =COUNTIF('Harvest Records'!B:B,A3) -> 3 | C3: =SUMIF('Harvest Records'!B:B,A3,'Harvest Records'!G:G) -> 389 | D3: kg | E3: =IFERROR(SUMIF('Harvest Records'!B:B,A3,'Harvest Records'!J:J)/C3,0) -> 105.24846 | F3: =SUMIF('Harvest Records'!B:B,A3,'Harvest Records'!J:J) -> 40941.65 | G3: =SUMIF('Harvest Records'!B:B,A3,'Harvest Records'!O:O) -> 47749.97 | H3: =F3-G3 -> -6808.32 | I3: =IFERROR(H3/F3*100,0) -> -16.629325
A4: Brinjal | B4: =COUNTIF('Harvest Records'!B:B,A4) -> 3 | C4: =SUMIF('Harvest Records'!B:B,A4,'Harvest Records'!G:G) -> 235 | D4: kg | E4: =IFERROR(SUMIF('Harvest Records'!B:B,A4,'Harvest Records'!J:J)/C4,0) -> 112.27387 | F4: =SUMIF('Harvest Records'!B:B,A4,'Harvest Records'!J:J) -> 26384.36 | G4: =SUMIF('Harvest Records'!B:B,A4,'Harvest Records'!O:O) -> 48465.74 | H4: =F4-G4 -> -22081.38 | I4: =IFERROR(H4/F4*100,0) -> -83.691172
A5: Beans | B5: =COUNTIF('Harvest Records'!B:B,A5) -> 4 | C5: =SUMIF('Harvest Records'!B:B,A5,'Harvest Records'!G:G) -> 266 | D5: kg | E5: =IFERROR(SUMIF('Harvest Records'!B:B,A5,'Harvest Records'!J:J)/C5,0) -> 237.88921 | F5: =SUMIF('Harvest Records'!B:B,A5,'Harvest Records'!J:J) -> 63278.53 | G5: =SUMIF('Harvest Records'!B:B,A5,'Harvest Records'!O:O) -> 36556.62 | H5: =F5-G5 -> 26721.91 | I5: =IFERROR(H5/F5*100,0) -> 42.229031
A6: Ladies Finger | B6: =COUNTIF('Harvest Records'!B:B,A6) -> 3 | C6: =SUMIF('Harvest Records'!B:B,A6,'Harvest Records'!G:G) -> 230 | D6: kg | E6: =IFERROR(SUMIF('Harvest Records'!B:B,A6,'Harvest Records'!J:J)/C6,0) -> 134.97413 | F6: =SUMIF('Harvest Records'!B:B,A6,'Harvest Records'!J:J) -> 31044.05 | G6: =SUMIF('Harvest Records'!B:B,A6,'Harvest Records'!O:O) -> 25977.22 | H6: =F6-G6 -> 5066.83 | I6: =IFERROR(H6/F6*100,0) -> 16.321421
A7: Corn | B7: =COUNTIF('Harvest Records'!B:B,A7) -> 3 | C7: =SUMIF('Harvest Records'!B:B,A7,'Harvest Records'!G:G) -> 472 | D7: kg | E7: =IFERROR(SUMIF('Harvest Records'!B:B,A7,'Harvest Records'!J:J)/C7,0) -> 83.053983 | F7: =SUMIF('Harvest Records'!B:B,A7,'Harvest Records'!J:J) -> 39201.48 | G7: =SUMIF('Harvest Records'!B:B,A7,'Harvest Records'!O:O) -> 63889.96 | H7: =F7-G7 -> -24688.48 | I7: =IFERROR(H7/F7*100,0) -> -62.978439
A8: Green Chilli | B8: =COUNTIF('Harvest Records'!B:B,A8) -> 3 | C8: =SUMIF('Harvest Records'!B:B,A8,'Harvest Records'!G:G) -> 183 | D8: kg | E8: =IFERROR(SUMIF('Harvest Records'!B:B,A8,'Harvest Records'!J:J)/C8,0) -> 276.5059 | F8: =SUMIF('Harvest Records'!B:B,A8,'Harvest Records'!J:J) -> 50600.58 | G8: =SUMIF('Harvest Records'!B:B,A8,'Harvest Records'!O:O) -> 32921.25 | H8: =F8-G8 -> 17679.33 | I8: =IFERROR(H8/F8*100,0) -> 34.938987
A9: Turmeric | B9: =COUNTIF('Harvest Records'!B:B,A9) -> 2 | C9: =SUMIF('Harvest Records'!B:B,A9,'Harvest Records'!G:G) -> 119 | D9: kg | E9: =IFERROR(SUMIF('Harvest Records'!B:B,A9,'Harvest Records'!J:J)/C9,0) -> 439.87412 | F9: =SUMIF('Harvest Records'!B:B,A9,'Harvest Records'!J:J) -> 52345.02 | G9: =SUMIF('Harvest Records'!B:B,A9,'Harvest Records'!O:O) -> 28621.1 | H9: =F9-G9 -> 23723.92 | I9: =IFERROR(H9/F9*100,0) -> 45.32221
A10: Papaya | B10: =COUNTIF('Harvest Records'!B:B,A10) -> 2 | C10: =SUMIF('Harvest Records'!B:B,A10,'Harvest Records'!G:G) -> 348 | D10: kg | E10: =IFERROR(SUMIF('Harvest Records'!B:B,A10,'Harvest Records'!J:J)/C10,0) -> 89.538161 | F10: =SUMIF('Harvest Records'!B:B,A10,'Harvest Records'!J:J) -> 31159.28 | G10: =SUMIF('Harvest Records'!B:B,A10,'Harvest Records'!O:O) -> 21573.08 | H10: =F10-G10 -> 9586.2 | I10: =IFERROR(H10/F10*100,0) -> 30.765152
A11: Mango | B11: =COUNTIF('Harvest Records'!B:B,A11) -> 2 | C11: =SUMIF('Harvest Records'!B:B,A11,'Harvest Records'!G:G) -> 287 | D11: kg | E11: =IFERROR(SUMIF('Harvest Records'!B:B,A11,'Harvest Records'!J:J)/C11,0) -> 220.21439 | F11: =SUMIF('Harvest Records'!B:B,A11,'Harvest Records'!J:J) -> 63201.53 | G11: =SUMIF('Harvest Records'!B:B,A11,'Harvest Records'!O:O) -> 23754.94 | H11: =F11-G11 -> 39446.59 | I11: =IFERROR(H11/F11*100,0) -> 62.41398
A12: Coconut | B12: =COUNTIF('Harvest Records'!B:B,A12) -> 2 | C12: =SUMIF('Harvest Records'!B:B,A12,'Harvest Records'!G:G) -> 569 | D12: nuts | E12: =IFERROR(SUMIF('Harvest Records'!B:B,A12,'Harvest Records'!J:J)/C12,0) -> 107.64649 | F12: =SUMIF('Harvest Records'!B:B,A12,'Harvest Records'!J:J) -> 61250.85 | G12: =SUMIF('Harvest Records'!B:B,A12,'Harvest Records'!O:O) -> 15905.61 | H12: =F12-G12 -> 45345.24 | I12: =IFERROR(H12/F12*100,0) -> 74.032018
A13: Lemon | B13: =COUNTIF('Harvest Records'!B:B,A13) -> 2 | C13: =SUMIF('Harvest Records'!B:B,A13,'Harvest Records'!G:G) -> 115 | D13: kg | E13: =IFERROR(SUMIF('Harvest Records'!B:B,A13,'Harvest Records'!J:J)/C13,0) -> 254.95757 | F13: =SUMIF('Harvest Records'!B:B,A13,'Harvest Records'!J:J) -> 29320.12 | G13: =SUMIF('Harvest Records'!B:B,A13,'Harvest Records'!O:O) -> 13600.72 | H13: =F13-G13 -> 15719.4 | I13: =IFERROR(H13/F13*100,0) -> 53.613014
A14: TOTAL | C14: =SUM(C2:C13) -> 4631 | F14: =SUM(F2:F13) -> 650637.91 | G14: =SUM(G2:G13) -> 601124.38 | H14: =SUM(H2:H13) -> 49513.53
